FlexPicLabel/__init__.py
FlexPicLabel-1.0.dist-info/LICENSE
FlexPicLabel-1.0.dist-info/METADATA
FlexPicLabel-1.0.dist-info/WHEEL
FlexPicLabel-1.0.dist-info/top_level.txt
FlexPicLabel-1.0.dist-info/RECORD
