Metadata-Version: 2.1
Name: FlexPicLabel
Version: 1.0
Summary: Flexible Lablel to put pictures in, for PYQT5
Home-page: UNKNOWN
Author: poshl9k
Author-email: poshl9k@gmail.com
License: UNKNOWN
Platform: UNKNOWN
Classifier: Programming Language :: Python :: 3
Classifier: License :: OSI Approved :: MIT License
Classifier: Operating System :: OS Independent
Requires-Python: >=3.6
